bottombar.py
bottombar-2.1.dist-info/LICENSE
bottombar-2.1.dist-info/WHEEL
bottombar-2.1.dist-info/METADATA
bottombar-2.1.dist-info/RECORD
