Metadata-Version: 2.1
Name: bottombar
Version: 2.1
Summary: Print and maintain a status line at the bottom of a VT100 terminal.
Author-email: Evalf <info@evalf.com>
Requires-Python: >=3
Classifier: License :: OSI Approved :: MIT License
Project-URL: Home, https://github.com/evalf/bottombar/
